indexer/LectureVideoIndexer.py
indexer/VideoConverter.py
indexer/__init__.py
indexer/cli.py
indexer/constants.py
indexer/test.py
indexer/video_converter.py
indexer/video_indexer.py
indexer/Types/Config.py
indexer/Types/Stage.py
indexer/Types/TableOfContents.py
indexer/Types/VideoIndexEntry.py
indexer/Types/__init__.py
indexer/processor/BasicFrameProcessor.py
indexer/processor/FrameProcessor.py
indexer/processor/TOCProcessor.py
indexer/processor/__init__.py
indexer/processor/basic_frame_preocessor.py
indexer/processor/frame_processor.py
indexer/processor/toc_processor.py
fit_lecture_indexer-0.2.0.dist-info/LICENSE.md
fit_lecture_indexer-0.2.0.dist-info/METADATA
fit_lecture_indexer-0.2.0.dist-info/WHEEL
fit_lecture_indexer-0.2.0.dist-info/top_level.txt
fit_lecture_indexer-0.2.0.dist-info/RECORD
