Metadata-Version: 2.1
Name: fit-lecture-indexer
Version: 0.2.0
Summary: A tool for extracting timestamps of slide transitions from a video lecture
Home-page: https://github.com/jstorm31/fit-lecture-indexer
Author: Jiří Zdvomka
Author-email: zdvomka.j@gmail.com
License: MIT
Platform: UNKNOWN
Classifier: Programming Language :: Python :: 3.8
License-File: LICENSE.md
Requires-Dist: tqdm
Requires-Dist: imagehash
Requires-Dist: strsimpy
Requires-Dist: opencv-python-headless
Requires-Dist: pytesseract
